CustomPygame/.idea/.gitignore
CustomPygame/.idea/inspectionProfiles/profiles_settings.xml
CustomPygame/.idea/misc.xml
CustomPygame/.idea/modules.xml
CustomPygame/.idea/MyEngine.iml
CustomPygame/.idea/workspace.xml
CustomPygame/events.py
CustomPygame/screen.py
CustomPygame/test.py
CustomPygame/Widgets/button.py
CustomPygame/Widgets/check_box.py
CustomPygame/Widgets/combo_box.py
CustomPygame/Widgets/label.py
CustomPygame/Widgets/themes.py
custompygame-0.0.1.dist-info/METADATA
custompygame-0.0.1.dist-info/WHEEL
custompygame-0.0.1.dist-info/RECORD
