Metadata-Version: 2.1
Name: custompygame
Version: 0.0.1
Summary: a miniature engine for python using the pygame library
Author: AndoR_21
Author-email: andorscomunityhelper@gmail.com
Requires-Python: >=3.10,<4.0
Classifier: Programming Language :: Python :: 3
Classifier: Programming Language :: Python :: 3.10
Classifier: Programming Language :: Python :: 3.11
